siginfo/__init__.py
siginfo/localclass.py
siginfo/siginfoclass.py
siginfo/utils.py
siginfo-0.10.dist-info/LICENSE
siginfo-0.10.dist-info/METADATA
siginfo-0.10.dist-info/WHEEL
siginfo-0.10.dist-info/top_level.txt
siginfo-0.10.dist-info/RECORD
