Metadata-Version: 2.1
Name: siginfo
Version: 0.10
Summary: A Python package to help debugging and monitoring python script
Author-email: Jonas Marcello <jonas.marcello@esbme.com>
License: MIT
Project-URL: Homepage, https://github.com/anergictcell/siginfo
Project-URL: Repository, https://github.com/anergictcell/siginfo
Project-URL: Bug Tracker, https://github.com/anergictcell/siginfo/issues
Project-URL: Documentation, https://siginfo.readthedocs.io/
Keywords: signal,debug,monitoring
Classifier: Development Status :: 4 - Beta
Classifier: Intended Audience :: Developers
Classifier: Intended Audience :: Science/Research
Classifier: Intended Audience :: System Administrators
Classifier: License :: OSI Approved :: MIT License
Classifier: Operating System :: MacOS :: MacOS X
Classifier: Operating System :: Unix
Classifier: Programming Language :: Python :: 3
Classifier: Programming Language :: Python :: Implementation :: CPython
Classifier: Programming Language :: Python :: Implementation :: PyPy
Classifier: Topic :: Software Development :: Bug Tracking
Classifier: Topic :: Software Development :: Debuggers
Classifier: Topic :: Software Development :: Libraries :: Python Modules
Classifier: Topic :: System :: Logging
Classifier: Topic :: System :: Monitoring
Requires-Python: >=3.7
License-File: LICENSE
